Metadata-Version: 2.4
Name: multimodal-agent-framework
Version: 0.1.10
Summary: A multi-modal agent framework with unified interfaces for different AI model providers
Author-email: Your Name <your.email@example.com>
License: MIT
Project-URL: Homepage, https://github.com/uditk2/multimodalagentframework
Project-URL: Bug Reports, https://github.com/uditk2/multimodalagentframework/issues
Project-URL: Source, https://github.com/uditk2/multimodalagentframework
Keywords: ai,agents,multimodal,openai,claude,azure
Classifier: Development Status :: 3 - Alpha
Classifier: Intended Audience :: Developers
Classifier: License :: OSI Approved :: MIT License
Classifier: Operating System :: OS Independent
Classifier: Programming Language :: Python :: 3
Classifier: Programming Language :: Python :: 3.9
Classifier: Programming Language :: Python :: 3.10
Classifier: Programming Language :: Python :: 3.11
Classifier: Programming Language :: Python :: 3.12
Classifier: Topic :: Software Development :: Libraries :: Python Modules
Classifier: Topic :: Scientific/Engineering :: Artificial Intelligence
Requires-Python: <3.13,>=3.9
License-File: LICENSE
Requires-Dist: openai>=1.99.0
Requires-Dist: anthropic>=0.67.0
Requires-Dist: azure-ai-inference==1.0.0b7
Requires-Dist: azure-core>=1.30.0
Requires-Dist: python-dotenv>=1.0.0
Requires-Dist: requests>=2.31.0
Requires-Dist: retrying>=1.3.3
Requires-Dist: typing-extensions>=4.8.0
Requires-Dist: pandas>=2.2.3
Requires-Dist: boto3>=1.34.0
Requires-Dist: pyarrow>=15.0.0
Provides-Extra: dev
Requires-Dist: pytest>=7.0; extra == "dev"
Requires-Dist: pytest-cov>=4.0; extra == "dev"
Requires-Dist: black>=22.0; extra == "dev"
Requires-Dist: flake8>=5.0; extra == "dev"
Requires-Dist: mypy>=1.0; extra == "dev"
Dynamic: license-file
